alil_simple_regressionxrion-1.0.0.dist-info/licenses/LICENSE.txt
simple_regression/__init__.py
simple_regression/regression.py
alil_simple_regressionxrion-1.0.0.dist-info/METADATA
alil_simple_regressionxrion-1.0.0.dist-info/WHEEL
alil_simple_regressionxrion-1.0.0.dist-info/top_level.txt
alil_simple_regressionxrion-1.0.0.dist-info/RECORD
