Metadata-Version: 2.4
Name: alil_simple_regressionxrion
Version: 1.0.0
Summary: Simple Linear Regression from scratch
Author: abd el jalil
License-File: LICENSE.txt
Dynamic: author
Dynamic: license-file
Dynamic: summary
